{
  "wireframe_visualization": {
    "layout": "single_column",
    "sections_order": [
      "global_header",
      "hero",
      "social_proof",
      "key_features",
      "social_proof_testimonial",
      "primary_cta_form",
      "global_footer"
    ],
    "section_heights": {
      "global_header": "80px",
      "hero": "600px",
      "social_proof": "200px",
      "key_features": "400px",
      "social_proof_testimonial": "300px",
      "primary_cta_form": "400px",
      "global_footer": "200px"
    },
    "spacing_between_sections": "80px",
    "container_width": {
      "mobile": "100%",
      "tablet": "90%",
      "desktop": "1200px"
    },
    "grid_system": {
      "columns": 12,
      "gutter": "24px",
      "margin": "16px"
    }
  }
}